mlflowlib/__init__.py
mlflowlib/training.py
mlflowlib-3.0.dist-info/LICENSE.txt
mlflowlib-3.0.dist-info/METADATA
mlflowlib-3.0.dist-info/WHEEL
mlflowlib-3.0.dist-info/top_level.txt
mlflowlib-3.0.dist-info/RECORD
