Metadata-Version: 2.1
Name: mlflowlib
Version: 3.0
Summary: a general-purpose python package with MLflow integration
Home-page: https://github.com/iremozdemr/mlflowlib
Download-URL: https://github.com/iremozdemr/mlflowlib/archive/refs/tags/3.0.tar.gz
Author: irem ozdemir
Author-email: iremozdemirwww3@gmail.com
License: MIT
Keywords: mlflow
License-File: LICENSE.txt
Requires-Dist: mlflow>=1.21.0
Requires-Dist: tensorflow>=2.5.0
